LICENSE
MANIFEST.in
README.md
setup.py
ultralyticsutils/.DS_Store
ultralyticsutils/__init__.py
ultralyticsutils/__version__.py
ultralyticsutils/core.py
ultralyticsutils.egg-info/PKG-INFO
ultralyticsutils.egg-info/SOURCES.txt
ultralyticsutils.egg-info/dependency_links.txt
ultralyticsutils.egg-info/top_level.txt
ultralyticsutils/assert/bus.jpg
ultralyticsutils/cfg/.DS_Store
ultralyticsutils/cfg/default.yaml
ultralyticsutils/cfg/datasets/coco128.yaml
ultralyticsutils/cfg/jupyter/.DS_Store
ultralyticsutils/cfg/jupyter/例1/.DS_Store
ultralyticsutils/cfg/jupyter/例1/数据预处理/.DS_Store
ultralyticsutils/cfg/jupyter/例1/数据预处理/数据预处理（答案）.ipynb
ultralyticsutils/cfg/jupyter/例1/数据预处理/数据预处理（问题）.ipynb
ultralyticsutils/cfg/jupyter/例1/数据预处理/.ipynb_checkpoints/数据预处理（问题）-checkpoint.ipynb
ultralyticsutils/cfg/jupyter/例1/机器学习/.DS_Store
ultralyticsutils/cfg/jupyter/例1/机器学习/机器学习答案.ipynb
ultralyticsutils/cfg/jupyter/例1/机器学习/机器学习答案.py
ultralyticsutils/cfg/jupyter/例1/机器学习/机器学习问题.ipynb
ultralyticsutils/cfg/jupyter/例1/机器学习/.ipynb_checkpoints/机器学习答案-checkpoint.ipynb
ultralyticsutils/cfg/jupyter/例1/机器学习/.ipynb_checkpoints/机器学习答案-checkpoint.py
ultralyticsutils/cfg/jupyter/例1/机器学习/.ipynb_checkpoints/机器学习问题-checkpoint.ipynb
ultralyticsutils/cfg/jupyter/例2/.DS_Store
ultralyticsutils/cfg/jupyter/例2/数据预处理/.DS_Store
ultralyticsutils/cfg/jupyter/例2/数据预处理/数据预处理 - 答案.ipynb
ultralyticsutils/cfg/jupyter/例2/数据预处理/数据预处理 - 题目.ipynb
ultralyticsutils/cfg/jupyter/例2/机器学习/.DS_Store
ultralyticsutils/cfg/jupyter/例2/机器学习/IS_Subscribe_答案.ipynb
ultralyticsutils/cfg/jupyter/例2/机器学习/IS_Subscribe_题目.ipynb
ultralyticsutils/cfg/jupyter/例2/机器学习/.ipynb_checkpoints/IS_Subscribe_答案-checkpoint.ipynb
ultralyticsutils/cfg/jupyter/例3/.DS_Store
ultralyticsutils/cfg/jupyter/例3/数据预处理/.DS_Store
ultralyticsutils/cfg/jupyter/例3/数据预处理/数据预处理（答案）.ipynb
ultralyticsutils/cfg/jupyter/例3/数据预处理/数据预处理（问题）.ipynb
ultralyticsutils/cfg/jupyter/例3/数据预处理/.ipynb_checkpoints/数据预处理（答案）-checkpoint.ipynb
ultralyticsutils/cfg/jupyter/例3/机器学习/.DS_Store
ultralyticsutils/cfg/jupyter/例3/机器学习/机器学习考试（答案）.ipynb
ultralyticsutils/cfg/jupyter/例3/机器学习/机器学习考试（问题）.ipynb
