Metadata-Version: 2.1
Name: ultralyticsutils
Version: 8.0.5
Summary: My short description for my project.
Home-page: https://github.com/ultralytics/ultralytics
Author: Awesome Soul
Author-email: hello@ultralytics.com
License: MIT
Classifier: License :: OSI Approved :: MIT License
Classifier: Programming Language :: Python
Classifier: Programming Language :: Python :: 3
Classifier: Programming Language :: Python :: 3.6
Classifier: Programming Language :: Python :: Implementation :: CPython
Classifier: Programming Language :: Python :: Implementation :: PyPy
Requires-Python: >=3.6.0
License-File: LICENSE
